walrus/__init__.py
walrus/apps.py
django_walrus-0.1.0.dist-info/METADATA
django_walrus-0.1.0.dist-info/WHEEL
django_walrus-0.1.0.dist-info/licenses/LICENSE
django_walrus-0.1.0.dist-info/RECORD
