Metadata-Version: 2.3
Name: django-walrus
Version: 0.1.0
Summary: Add assignment expressions (walrus operator) to Django templates
Project-URL: Homepage, https://github.com/bmispelon/django-walrus
Project-URL: Issues, https://github.com/bmispelon/django-walrus/issues
Author-email: Baptiste Mispelon <bmispelon@gmail.com>
License: MIT License
License-File: LICENSE
Keywords: assignment expression,django,walrus
Classifier: Framework :: Django
Classifier: License :: OSI Approved :: MIT License
Classifier: Operating System :: OS Independent
Classifier: Programming Language :: Python :: 3
Requires-Python: >=3.8
Provides-Extra: dev
Requires-Dist: pytest; extra == 'dev'
